pycuber/__init__.py
pycuber/cube.py
pycuber/formula.py
pycuber/helpers.py
pycuber/util.py
pycuber/solver/__init__.py
pycuber/solver/cfop/__init__.py
pycuber/solver/cfop/cross.py
pycuber/solver/cfop/f2l.py
pycuber/solver/cfop/oll.py
pycuber/solver/cfop/oll_algos.csv
pycuber/solver/cfop/pll.py
pycuber/solver/cfop/pll_algos.csv
pycuber/solver/cfop/util.py
pycuber-0.2.2.dist-info/DESCRIPTION.rst
pycuber-0.2.2.dist-info/METADATA
pycuber-0.2.2.dist-info/RECORD
pycuber-0.2.2.dist-info/WHEEL
pycuber-0.2.2.dist-info/metadata.json
pycuber-0.2.2.dist-info/top_level.txt
