Metadata-Version: 1.1
Name: pycuber
Version: 0.2.2
Summary: Rubik's Cube in Python
Home-page: http://github.com/adrianliaw/PyCuber
Author: Adrian Liaw
Author-email: adrianliaw2000@gmail.com
License: MIT
Keywords: Rubik's Cube,rubik,cube,solver
Platform: UNKNOWN
Classifier: Development Status :: 4 - Beta
Classifier: Environment :: Console
Classifier: Intended Audience :: Science/Research
Classifier: License :: OSI Approved :: MIT License
Classifier: Programming Language :: Python
Classifier: Programming Language :: Python :: 2
Classifier: Programming Language :: Python :: 3
Classifier: Topic :: Scientific/Engineering :: Mathematics
